Metadata-Version: 1.1
Name: django_bootstrap_breadcrumbs
Version: 0.9.2
Summary: Django breadcrumbs for Bootstrap 2, 3 or 4
Home-page: http://prymitive.github.com/bootstrap-breadcrumbs
Author: Łukasz Mierzwa
Author-email: l.mierzwa@gmail.com
License: MIT
Platform: any
Classifier: License :: OSI Approved :: MIT License
Classifier: Intended Audience :: Developers
Classifier: Programming Language :: Python :: 2
Classifier: Programming Language :: Python :: 3
Classifier: Topic :: Software Development :: Libraries :: Python Modules
